hiagent_sdk/__init__.py
hiagent_sdk/client.py
hiagent_sdk/proxy.py
hiagent_sdk/models/__init__.py
hiagent_sdk/models/workflow.py
hiagent_sdk/parser/__init__.py
hiagent_sdk/utils/__init__.py
hiagent_sdk/utils/http_client.py
hiagent_sdk-0.1.3.dist-info/METADATA
hiagent_sdk-0.1.3.dist-info/WHEEL
hiagent_sdk-0.1.3.dist-info/RECORD
